<?xml version="1.0" encoding="UTF-8"?><?xml-stylesheet type='text/xsl' href='_UpgradeReport_Files/UpgradeReport.xslt'?><UpgradeLog>
<Properties><Property Name="Solution" Value="Edpcom">
</Property><Property Name="Solution File" Value="E:\Project 23.12.14\Accord Four Project 2014 Dec 18\Edpcom\Edpcom\Edpcom.sln">
</Property><Property Name="User Options File" Value="E:\Project 23.12.14\Accord Four Project 2014 Dec 18\Edpcom\Edpcom\Edpcom.suo">
</Property><Property Name="Date" Value="Monday, January 05, 2015">
</Property><Property Name="Time" Value="15:33 PM">
</Property></Properties><Event ErrorLevel="0" Project="" Source="Edpcom.sln" Description="File successfully backed up as E:\Project 23.12.14\Accord Four Project 2014 Dec 18\Edpcom\Edpcom\Backup\Edpcom.sln">
</Event><Event ErrorLevel="0" Project="" Source="Edpcom.suo" Description="File successfully backed up as E:\Project 23.12.14\Accord Four Project 2014 Dec 18\Edpcom\Edpcom\Backup\Edpcom.suo">
</Event><Event ErrorLevel="0" Project="Edpcom" Source="Edpcom.csproj" Description="Project file successfully backed up as E:\Project 23.12.14\Accord Four Project 2014 Dec 18\Edpcom\Edpcom\Backup\Edpcom.csproj">
</Event><Event ErrorLevel="0" Project="Edpcom" Source="ConfigChk.cs" Description="File successfully backed up as E:\Project 23.12.14\Accord Four Project 2014 Dec 18\Edpcom\Edpcom\Backup\ConfigChk.cs">
</Event><Event ErrorLevel="0" Project="Edpcom" Source="EDPConnection.cs" Description="File successfully backed up as E:\Project 23.12.14\Accord Four Project 2014 Dec 18\Edpcom\Edpcom\Backup\EDPConnection.cs">
</Event><Event ErrorLevel="0" Project="Edpcom" Source="EDPCommon.cs" Description="File successfully backed up as E:\Project 23.12.14\Accord Four Project 2014 Dec 18\Edpcom\Edpcom\Backup\EDPCommon.cs">
</Event><Event ErrorLevel="0" Project="Edpcom" Source="frmActiveMainSubGrp.cs" Description="File successfully backed up as E:\Project 23.12.14\Accord Four Project 2014 Dec 18\Edpcom\Edpcom\Backup\frmActiveMainSubGrp.cs">
</Event><Event ErrorLevel="0" Project="Edpcom" Source="frmActiveMainSubGrp.designer.cs" Description="File successfully backed up as E:\Project 23.12.14\Accord Four Project 2014 Dec 18\Edpcom\Edpcom\Backup\frmActiveMainSubGrp.designer.cs">
</Event><Event ErrorLevel="0" Project="Edpcom" Source="frmConfigarationVariable.cs" Description="File successfully backed up as E:\Project 23.12.14\Accord Four Project 2014 Dec 18\Edpcom\Edpcom\Backup\frmConfigarationVariable.cs">
</Event><Event ErrorLevel="0" Project="Edpcom" Source="frmListAddRemoveTree.cs" Description="File successfully backed up as E:\Project 23.12.14\Accord Four Project 2014 Dec 18\Edpcom\Edpcom\Backup\frmListAddRemoveTree.cs">
</Event><Event ErrorLevel="0" Project="Edpcom" Source="frmListAddRemoveTree.Designer.cs" Description="File successfully backed up as E:\Project 23.12.14\Accord Four Project 2014 Dec 18\Edpcom\Edpcom\Backup\frmListAddRemoveTree.Designer.cs">
</Event><Event ErrorLevel="0" Project="Edpcom" Source="Properties\AssemblyInfo.cs" Description="File successfully backed up as E:\Project 23.12.14\Accord Four Project 2014 Dec 18\Edpcom\Edpcom\Backup\Properties\AssemblyInfo.cs">
</Event><Event ErrorLevel="0" Project="Edpcom" Source="ItemSelaction.cs" Description="File successfully backed up as E:\Project 23.12.14\Accord Four Project 2014 Dec 18\Edpcom\Edpcom\Backup\ItemSelaction.cs">
</Event><Event ErrorLevel="0" Project="Edpcom" Source="ItemSelaction.designer.cs" Description="File successfully backed up as E:\Project 23.12.14\Accord Four Project 2014 Dec 18\Edpcom\Edpcom\Backup\ItemSelaction.designer.cs">
</Event><Event ErrorLevel="0" Project="Edpcom" Source="Properties\Resources.Designer.cs" Description="File successfully backed up as E:\Project 23.12.14\Accord Four Project 2014 Dec 18\Edpcom\Edpcom\Backup\Properties\Resources.Designer.cs">
</Event><Event ErrorLevel="0" Project="Edpcom" Source="Money.ico" Description="File successfully backed up as E:\Project 23.12.14\Accord Four Project 2014 Dec 18\Edpcom\Edpcom\Backup\Money.ico">
</Event><Event ErrorLevel="0" Project="Edpcom" Source="frmActiveMainSubGrp.resx" Description="File successfully backed up as E:\Project 23.12.14\Accord Four Project 2014 Dec 18\Edpcom\Edpcom\Backup\frmActiveMainSubGrp.resx">
</Event><Event ErrorLevel="0" Project="Edpcom" Source="frmListAddRemoveTree.resx" Description="File successfully backed up as E:\Project 23.12.14\Accord Four Project 2014 Dec 18\Edpcom\Edpcom\Backup\frmListAddRemoveTree.resx">
</Event><Event ErrorLevel="0" Project="Edpcom" Source="ItemSelaction.resx" Description="File successfully backed up as E:\Project 23.12.14\Accord Four Project 2014 Dec 18\Edpcom\Edpcom\Backup\ItemSelaction.resx">
</Event><Event ErrorLevel="0" Project="Edpcom" Source="Properties\Resources.resx" Description="File successfully backed up as E:\Project 23.12.14\Accord Four Project 2014 Dec 18\Edpcom\Edpcom\Backup\Properties\Resources.resx">
</Event><Event ErrorLevel="0" Project="Edpcom" Source="Edpcom.csproj" Description="Project converted successfully">
</Event><Event ErrorLevel="3" Project="Edpcom" Source="Edpcom.csproj" Description="Converted">
</Event><Event ErrorLevel="0" Project="" Source="Edpcom.sln" Description="Solution converted successfully">
</Event><Event ErrorLevel="3" Project="" Source="Edpcom.sln" Description="Converted">
</Event><Event ErrorLevel="0" Project="Edpcom" Source="Edpcom.csproj" Description="Scan complete: Upgrade not required for project files.">
</Event></UpgradeLog>